stp/__init__.py
stp/stp.py
stp/utils.py
semi_tensor_product-0.0.4.dist-info/LICENSES
semi_tensor_product-0.0.4.dist-info/METADATA
semi_tensor_product-0.0.4.dist-info/WHEEL
semi_tensor_product-0.0.4.dist-info/top_level.txt
semi_tensor_product-0.0.4.dist-info/RECORD
