Metadata-Version: 2.1
Name: semi-tensor-product
Version: 0.0.4
Summary: STP Toolbox for Python
Home-page: https://github.com/huanianss/semi-tensor-product
Author: Huanianss
Author-email: huanianss@qq.com
Project-URL: Bug Tracker, https://github.com/huanianss/semi-tensor-product/issues
Classifier: Programming Language :: Python :: 3
Classifier: License :: OSI Approved :: MIT License
Classifier: Operating System :: OS Independent
Requires-Python: >=3.6
License-File: LICENSES
